LICENCE.txt
MANIFEST.in
README.rst
setup.cfg
setup.py
deovi/__init__.py
deovi/exceptions.py
deovi/logger.py
deovi/scrapper.py
deovi.egg-info/PKG-INFO
deovi.egg-info/SOURCES.txt
deovi.egg-info/dependency_links.txt
deovi.egg-info/entry_points.txt
deovi.egg-info/requires.txt
deovi.egg-info/top_level.txt
deovi.egg-info/zip-safe
deovi/cli/__init__.py
deovi/cli/collect.py
deovi/cli/entrypoint.py
deovi/cli/job.py
deovi/cli/rename.py
deovi/cli/scrap.py
deovi/cli/version.py
deovi/collector/__init__.py
deovi/collector/collect.py
deovi/collector/storage.py
deovi/renamer/__init__.py
deovi/renamer/jobs.py
deovi/renamer/printer.py
deovi/renamer/runner.py
deovi/renamer/tasks.py
deovi/renamer/validators.py
deovi/utils/__init__.py
deovi/utils/checksum.py
deovi/utils/jsons.py
deovi/utils/tests.py