Metadata-Version: 2.1
Name: deovi
Version: 0.6.1
Summary: Utility to rename files and collect their filepaths
Home-page: https://github.com/sveetch/deovi
Author: David Thenon
Author-email: sveetch@gmail.com
License: MIT
Keywords: Python
Classifier: Development Status :: 5 - Production/Stable
Classifier: Intended Audience :: Developers
Classifier: License :: OSI Approved :: MIT License
Classifier: Natural Language :: English
Classifier: Programming Language :: Python :: 3
Classifier: Programming Language :: Python :: 3.8
Classifier: Programming Language :: Python :: 3.9
Classifier: Programming Language :: Python :: 3.10
Provides-Extra: scrapping
Provides-Extra: dev
Provides-Extra: quality
Provides-Extra: doc
Provides-Extra: release
License-File: LICENCE.txt
